{"url": "https://api.github.com/repos/quantopian/zipline/pulls/2818", "id": 617551806, "node_id": "MDExOlB1bGxSZXF1ZXN0NjE3NTUxODA2", "html_url": "https://github.com/quantopian/zipline/pull/2818", "diff_url": "https://github.com/quantopian/zipline/pull/2818.diff", "patch_url": "https://github.com/quantopian/zipline/pull/2818.patch", "issue_url": "https://api.github.com/repos/quantopian/zipline/issues/2818", "number": 2818, "state": "closed", "locked": false, "title": "add pyfolio into docker image build", "user": {"login": "stanleyu911", "id": 63316944, "node_id": "MDQ6VXNlcjYzMzE2OTQ0", "avatar_url": "https://avatars.githubusercontent.com/u/63316944?v=4", "gravatar_id": "", "url": "https://api.github.com/users/stanleyu911", "html_url": "https://github.com/stanleyu911", "followers_url": "https://api.github.com/users/stanleyu911/followers", "following_url": "https://api.github.com/users/stanleyu911/following{/other_user}", "gists_url": "https://api.github.com/users/stanleyu911/gists{/gist_id}", "starred_url": "https://api.github.com/users/stanleyu911/starred{/owner}{/repo}", "subscriptions_url": "https://api.github.com/users/stanleyu911/subscriptions", "organizations_url": "https://api.github.com/users/stanleyu911/orgs", "repos_url": "https://api.github.com/users/stanleyu911/repos", "events_url": "https://api.github.com/users/stanleyu911/events{/privacy}", "received_events_url": "https://api.github.com/users/stanleyu911/received_events", "type": "User", "user_view_type": "public", "site_admin": false}, "body": "", "created_at": "2021-04-18T20:39:59Z", "updated_at": "2021-04-18T20:40:40Z", "closed_at": "2021-04-18T20:40:40Z", "merged_at": null, "merge_commit_sha": "57d2fd6926a694f3a8e6010dee7192569d5a0286", "assignee": null, "assignees": [], "requested_reviewers": [], "requested_teams": [], "labels": [], "milestone": null, "draft": false, "commits_url": "https://api.github.com/repos/quantopian/zipline/pulls/2818/commits", "review_comments_url": "https://api.github.com/repos/quantopian/zipline/pulls/2818/comments", "review_comment_url": "https://api.github.com/repos/quantopian/zipline/pulls/comments{/number}", "comments_url": "https://api.github.com/repos/quantopian/zipline/issues/2818/comments", "statuses_url": "https://api.github.com/repos/quantopian/zipline/statuses/8626f9b99afceebe2bf18d7f2828681460f3984a", "head": {"label": "stanleyu911:develop", "ref": "develop", "sha": "8626f9b99afceebe2bf18d7f2828681460f3984a", "user": {"login": "stanleyu911", "id": 63316944, "node_id": "MDQ6VXNlcjYzMzE2OTQ0", "avatar_url": "https://avatars.githubusercontent.com/u/63316944?v=4", "gravatar_id": "", "url": "https://api.github.com/users/stanleyu911", "html_url": "https://github.com/stanleyu911", "followers_url": "https://api.github.com/users/stanleyu911/followers", "following_url": "https://api.github.com/users/stanleyu911/following{/other_user}", "gists_url": "https://api.github.com/users/stanleyu911/gists{/gist_id}", "starred_url": "https://api.github.com/users/stanleyu911/starred{/owner}{/repo}", "subscriptions_url": "https://api.github.com/users/stanleyu911/subscriptions", "organizations_url": "https://api.github.com/users/stanleyu911/orgs", "repos_url": "https://api.github.com/users/stanleyu911/repos", "events_url": "https://api.github.com/users/stanleyu911/events{/privacy}", "received_events_url": "https://api.github.com/users/stanleyu911/received_events", "type": "User", "user_view_type": "public", "site_admin": false}, "repo": {"id": 354384123, "node_id": "MDEwOlJlcG9zaXRvcnkzNTQzODQxMjM=", "name": "zipline", "full_name": "stanleyu911/zipline", "private": false, "owner": {"login": "stanleyu911", "id": 63316944, "node_id": "MDQ6VXNlcjYzMzE2OTQ0", "avatar_url": "https://avatars.githubusercontent.com/u/63316944?v=4", "gravatar_id": "", "url": "https://api.github.com/users/stanleyu911", "html_url": "https://github.com/stanleyu911", "followers_url": "https://api.github.com/users/stanleyu911/followers", "following_url": "https://api.github.com/users/stanleyu911/following{/other_user}", "gists_url": "https://api.github.com/users/stanleyu911/gists{/gist_id}", "starred_url": "https://api.github.com/users/stanleyu911/starred{/owner}{/repo}", "subscriptions_url": "https://api.github.com/users/stanleyu911/subscriptions", "organizations_url": "https://api.github.com/users/stanleyu911/orgs", "repos_url": "https://api.github.com/users/stanleyu911/repos", "events_url": "https://api.github.com/users/stanleyu911/events{/privacy}", "received_events_url": "https://api.github.com/users/stanleyu911/received_events", "type": "User", "user_view_type": "public", "site_admin": false}, "html_url": "https://github.com/stanleyu911/zipline", "description": "Zipline, a Pythonic Algorithmic Trading Library", "fork": true, "url": "https://api.github.com/repos/stanleyu911/zipline", "forks_url": "https://api.github.com/repos/stanleyu911/zipline/forks", "keys_url": "https://api.github.com/repos/stanleyu911/zipline/keys{/key_id}", "collaborators_url": "https://api.github.com/repos/stanleyu911/zipline/collaborators{/collaborator}", "teams_url": "https://api.github.com/repos/stanleyu911/zipline/teams", "hooks_url": "https://api.github.com/repos/stanleyu911/zipline/hooks", "issue_events_url": "https://api.github.com/repos/stanleyu911/zipline/issues/events{/number}", "events_url": "https://api.github.com/repos/stanleyu911/zipline/events", "assignees_url": "https://api.github.com/repos/stanleyu911/zipline/assignees{/user}", "branches_url": "https://api.github.com/repos/stanleyu911/zipline/branches{/branch}", "tags_url": "https://api.github.com/repos/stanleyu911/zipline/tags", "blobs_url": "https://api.github.com/repos/stanleyu911/zipline/git/blobs{/sha}", "git_tags_url": "https://api.github.com/repos/stanleyu911/zipline/git/tags{/sha}", "git_refs_url": "https://api.github.com/repos/stanleyu911/zipline/git/refs{/sha}", "trees_url": "https://api.github.com/repos/stanleyu911/zipline/git/trees{/sha}", "statuses_url": "https://api.github.com/repos/stanleyu911/zipline/statuses/{sha}", "languages_url": "https://api.github.com/repos/stanleyu911/zipline/languages", "stargazers_url": "https://api.github.com/repos/stanleyu911/zipline/stargazers", "contributors_url": "https://api.github.com/repos/stanleyu911/zipline/contributors", "subscribers_url": "https://api.github.com/repos/stanleyu911/zipline/subscribers", "subscription_url": "https://api.github.com/repos/stanleyu911/zipline/subscription", "commits_url": "https://api.github.com/repos/stanleyu911/zipline/commits{/sha}", "git_commits_url": "https://api.github.com/repos/stanleyu911/zipline/git/commits{/sha}", "comments_url": "https://api.github.com/repos/stanleyu911/zipline/comments{/number}", "issue_comment_url": "https://api.github.com/repos/stanleyu911/zipline/issues/comments{/number}", "contents_url": "https://api.github.com/repos/stanleyu911/zipline/contents/{+path}", "compare_url": "https://api.github.com/repos/stanleyu911/zipline/compare/{base}...{head}", "merges_url": "https://api.github.com/repos/stanleyu911/zipline/merges", "archive_url": "https://api.github.com/repos/stanleyu911/zipline/{archive_format}{/ref}", "downloads_url": "https://api.github.com/repos/stanleyu911/zipline/downloads", "issues_url": "https://api.github.com/repos/stanleyu911/zipline/issues{/number}", "pulls_url": "https://api.github.com/repos/stanleyu911/zipline/pulls{/number}", "milestones_url": "https://api.github.com/repos/stanleyu911/zipline/milestones{/number}", "notifications_url": "https://api.github.com/repos/stanleyu911/zipline/notifications{?since,all,participating}", "labels_url": "https://api.github.com/repos/stanleyu911/zipline/labels{/name}", "releases_url": "https://api.github.com/repos/stanleyu911/zipline/releases{/id}", "deployments_url": "https://api.github.com/repos/stanleyu911/zipline/deployments", "created_at": "2021-04-03T20:06:32Z", "updated_at": "2021-04-18T22:07:32Z", "pushed_at": "2021-04-25T17:41:06Z", "git_url": "git://github.com/stanleyu911/zipline.git", "ssh_url": "git@github.com:stanleyu911/zipline.git", "clone_url": "https://github.com/stanleyu911/zipline.git", "svn_url": "https://github.com/stanleyu911/zipline", "homepage": "https://www.zipline.io", "size": 170996, "stargazers_count": 0, "watchers_count": 0, "language": "Python", "has_issues": false, "has_projects": true, "has_downloads": true, "has_wiki": false, "has_pages": false, "has_discussions": false, "forks_count": 0, "mirror_url": null, "archived": false, "disabled": false, "open_issues_count": 0, "license": {"key": "apache-2.0", "name": "Apache License 2.0", "spdx_id": "Apache-2.0", "url": "https://api.github.com/licenses/apache-2.0", "node_id": "MDc6TGljZW5zZTI="}, "allow_forking": true, "is_template": false, "web_commit_signoff_required": false, "topics": [], "visibility": "public", "forks": 0, "open_issues": 0, "watchers": 0, "default_branch": "master"}}, "base": {"label": "quantopian:master", "ref": "master", "sha": "014f1fc339dc8b7671d29be2d85ce57d3daec343", "user": {"login": "quantopian", "id": 1393215, "node_id": "MDEyOk9yZ2FuaXphdGlvbjEzOTMyMTU=", "avatar_url": "https://avatars.githubusercontent.com/u/1393215?v=4", "gravatar_id": "", "url": "https://api.github.com/users/quantopian", "html_url": "https://github.com/quantopian", "followers_url": "https://api.github.com/users/quantopian/followers", "following_url": "https://api.github.com/users/quantopian/following{/other_user}", "gists_url": "https://api.github.com/users/quantopian/gists{/gist_id}", "starred_url": "https://api.github.com/users/quantopian/starred{/owner}{/repo}", "subscriptions_url": "https://api.github.com/users/quantopian/subscriptions", "organizations_url": "https://api.github.com/users/quantopian/orgs", "repos_url": "https://api.github.com/users/quantopian/repos", "events_url": "https://api.github.com/users/quantopian/events{/privacy}", "received_events_url": "https://api.github.com/users/quantopian/received_events", "type": "Organization", "user_view_type": "public", "site_admin": false}, "repo": {"id": 6297520, "node_id": "MDEwOlJlcG9zaXRvcnk2Mjk3NTIw", "name": "zipline", "full_name": "quantopian/zipline", "private": false, "owner": {"login": "quantopian", "id": 1393215, "node_id": "MDEyOk9yZ2FuaXphdGlvbjEzOTMyMTU=", "avatar_url": "https://avatars.githubusercontent.com/u/1393215?v=4", "gravatar_id": "", "url": "https://api.github.com/users/quantopian", "html_url": "https://github.com/quantopian", "followers_url": "https://api.github.com/users/quantopian/followers", "following_url": "https://api.github.com/users/quantopian/following{/other_user}", "gists_url": "https://api.github.com/users/quantopian/gists{/gist_id}", "starred_url": "https://api.github.com/users/quantopian/starred{/owner}{/repo}", "subscriptions_url": "https://api.github.com/users/quantopian/subscriptions", "organizations_url": "https://api.github.com/users/quantopian/orgs", "repos_url": "https://api.github.com/users/quantopian/repos", "events_url": "https://api.github.com/users/quantopian/events{/privacy}", "received_events_url": "https://api.github.com/users/quantopian/received_events", "type": "Organization", "user_view_type": "public", "site_admin": false}, "html_url": "https://github.com/quantopian/zipline", "description": "Zipline, a Pythonic Algorithmic Trading Library", "fork": false, "url": "https://api.github.com/repos/quantopian/zipline", "forks_url": "https://api.github.com/repos/quantopian/zipline/forks", "keys_url": "https://api.github.com/repos/quantopian/zipline/keys{/key_id}", "collaborators_url": "https://api.github.com/repos/quantopian/zipline/collaborators{/collaborator}", "teams_url": "https://api.github.com/repos/quantopian/zipline/teams", "hooks_url": "https://api.github.com/repos/quantopian/zipline/hooks", "issue_events_url": "https://api.github.com/repos/quantopian/zipline/issues/events{/number}", "events_url": "https://api.github.com/repos/quantopian/zipline/events", "assignees_url": "https://api.github.com/repos/quantopian/zipline/assignees{/user}", "branches_url": "https://api.github.com/repos/quantopian/zipline/branches{/branch}", "tags_url": "https://api.github.com/repos/quantopian/zipline/tags", "blobs_url": "https://api.github.com/repos/quantopian/zipline/git/blobs{/sha}", "git_tags_url": "https://api.github.com/repos/quantopian/zipline/git/tags{/sha}", "git_refs_url": "https://api.github.com/repos/quantopian/zipline/git/refs{/sha}", "trees_url": "https://api.github.com/repos/quantopian/zipline/git/trees{/sha}", "statuses_url": "https://api.github.com/repos/quantopian/zipline/statuses/{sha}", "languages_url": "https://api.github.com/repos/quantopian/zipline/languages", "stargazers_url": "https://api.github.com/repos/quantopian/zipline/stargazers", "contributors_url": "https://api.github.com/repos/quantopian/zipline/contributors", "subscribers_url": "https://api.github.com/repos/quantopian/zipline/subscribers", "subscription_url": "https://api.github.com/repos/quantopian/zipline/subscription", "commits_url": "https://api.github.com/repos/quantopian/zipline/commits{/sha}", "git_commits_url": "https://api.github.com/repos/quantopian/zipline/git/commits{/sha}", "comments_url": "https://api.github.com/repos/quantopian/zipline/comments{/number}", "issue_comment_url": "https://api.github.com/repos/quantopian/zipline/issues/comments{/number}", "contents_url": "https://api.github.com/repos/quantopian/zipline/contents/{+path}", "compare_url": "https://api.github.com/repos/quantopian/zipline/compare/{base}...{head}", "merges_url": "https://api.github.com/repos/quantopian/zipline/merges", "archive_url": "https://api.github.com/repos/quantopian/zipline/{archive_format}{/ref}", "downloads_url": "https://api.github.com/repos/quantopian/zipline/downloads", "issues_url": "https://api.github.com/repos/quantopian/zipline/issues{/number}", "pulls_url": "https://api.github.com/repos/quantopian/zipline/pulls{/number}", "milestones_url": "https://api.github.com/repos/quantopian/zipline/milestones{/number}", "notifications_url": "https://api.github.com/repos/quantopian/zipline/notifications{?since,all,participating}", "labels_url": "https://api.github.com/repos/quantopian/zipline/labels{/name}", "releases_url": "https://api.github.com/repos/quantopian/zipline/releases{/id}", "deployments_url": "https://api.github.com/repos/quantopian/zipline/deployments", "created_at": "2012-10-19T15:50:29Z", "updated_at": "2026-01-18T22:48:07Z", "pushed_at": "2024-02-13T08:02:51Z", "git_url": "git://github.com/quantopian/zipline.git", "ssh_url": "git@github.com:quantopian/zipline.git", "clone_url": "https://github.com/quantopian/zipline.git", "svn_url": "https://github.com/quantopian/zipline", "homepage": "https://www.zipline.io", "size": 170757, "stargazers_count": 19346, "watchers_count": 19346, "language": "Python", "has_issues": true, "has_projects": true, "has_downloads": true, "has_wiki": false, "has_pages": true, "has_discussions": false, "forks_count": 4937, "mirror_url": null, "archived": false, "disabled": false, "open_issues_count": 366, "license": {"key": "apache-2.0", "name": "Apache License 2.0", "spdx_id": "Apache-2.0", "url": "https://api.github.com/licenses/apache-2.0", "node_id": "MDc6TGljZW5zZTI="}, "allow_forking": true, "is_template": false, "web_commit_signoff_required": false, "topics": ["algorithmic-trading", "python", "quant", "zipline"], "visibility": "public", "forks": 4937, "open_issues": 366, "watchers": 19346, "default_branch": "master"}}, "_links": {"self": {"href": "https://api.github.com/repos/quantopian/zipline/pulls/2818"}, "html": {"href": "https://github.com/quantopian/zipline/pull/2818"}, "issue": {"href": "https://api.github.com/repos/quantopian/zipline/issues/2818"}, "comments": {"href": "https://api.github.com/repos/quantopian/zipline/issues/2818/comments"}, "review_comments": {"href": "https://api.github.com/repos/quantopian/zipline/pulls/2818/comments"}, "review_comment": {"href": "https://api.github.com/repos/quantopian/zipline/pulls/comments{/number}"}, "commits": {"href": "https://api.github.com/repos/quantopian/zipline/pulls/2818/commits"}, "statuses": {"href": "https://api.github.com/repos/quantopian/zipline/statuses/8626f9b99afceebe2bf18d7f2828681460f3984a"}}, "author_association": "NONE", "auto_merge": null, "active_lock_reason": null, "merged": false, "mergeable": true, "rebaseable": false, "mergeable_state": "unstable", "merged_by": null, "comments": 0, "review_comments": [], "maintainer_can_modify": false, "commits": 1, "additions": 3, "deletions": 0, "changed_files": 1, "reviews": []}