{"url": "https://api.github.com/repos/stripe/stripe-python/pulls/1526", "id": 2574203393, "node_id": "PR_kwDOAB3Obc6ZbzoB", "html_url": "https://github.com/stripe/stripe-python/pull/1526", "diff_url": "https://github.com/stripe/stripe-python/pull/1526.diff", "patch_url": "https://github.com/stripe/stripe-python/pull/1526.patch", "issue_url": "https://api.github.com/repos/stripe/stripe-python/issues/1526", "number": 1526, "state": "closed", "locked": false, "title": "Update generated code", "user": {"login": "stripe-openapi[bot]", "id": 105521251, "node_id": "BOT_kgDOBkogYw", "avatar_url": "https://avatars.githubusercontent.com/in/200680?v=4", "gravatar_id": "", "url": "https://api.github.com/users/stripe-openapi%5Bbot%5D", "html_url": "https://github.com/apps/stripe-openapi", "followers_url": "https://api.github.com/users/stripe-openapi%5Bbot%5D/followers", "following_url": "https://api.github.com/users/stripe-openapi%5Bbot%5D/following{/other_user}", "gists_url": "https://api.github.com/users/stripe-openapi%5Bbot%5D/gists{/gist_id}", "starred_url": "https://api.github.com/users/stripe-openapi%5Bbot%5D/starred{/owner}{/repo}", "subscriptions_url": "https://api.github.com/users/stripe-openapi%5Bbot%5D/subscriptions", "organizations_url": "https://api.github.com/users/stripe-openapi%5Bbot%5D/orgs", "repos_url": "https://api.github.com/users/stripe-openapi%5Bbot%5D/repos", "events_url": "https://api.github.com/users/stripe-openapi%5Bbot%5D/events{/privacy}", "received_events_url": "https://api.github.com/users/stripe-openapi%5Bbot%5D/received_events", "type": "Bot", "user_view_type": "public", "site_admin": false}, "body": "Codegen for openapi v1819 and proto spec 2025-06-30.basil.\n\n## Changelog\n* Add support for `migrate` method on resource `Subscription`\n* Add support for `collect_payment_method` and `confirm_payment_intent` methods on resource `terminal.Reader`\n* Add support for `crypto_payments` on `Account.Capability`, `Account.CreateParamsCapability`, and `Account.ModifyParamsCapability`\n* Add support for `proof_of_address` on `Account.CreateParamsDocument` and `Account.ModifyParamsDocument`\n* Add support for `monthly_payout_days` and `weekly_payout_days` on `Account.CreateParamsSettingPayoutSchedule`, `Account.ModifyParamsSettingPayoutSchedule`, and `Account.Setting.Payout.Schedule`\n* Change `Account.Setting.Invoice.hosted_payment_method_save` to be required\n* Add support for `crypto` on `Charge.PaymentMethodDetail`, `ConfirmationToken.CreateParamsPaymentMethodDatum`, `ConfirmationToken.PaymentMethodPreview`, `PaymentIntent.ConfirmParamsPaymentMethodDatum`, `PaymentIntent.ConfirmParamsPaymentMethodOption`, `PaymentIntent.CreateParamsPaymentMethodDatum`, `PaymentIntent.CreateParamsPaymentMethodOption`, `PaymentIntent.ModifyParamsPaymentMethodDatum`, `PaymentIntent.ModifyParamsPaymentMethodOption`, `PaymentIntent.PaymentMethodOption`, `PaymentMethod.CreateParams`, `PaymentMethod`, `SetupIntent.ConfirmParamsPaymentMethodDatum`, `SetupIntent.CreateParamsPaymentMethodDatum`, and `SetupIntent.ModifyParamsPaymentMethodDatum`\n* Change type of `Charge.PaymentMethodDetail.Card.Installment.Plan.type`, `ConfirmationToken.CreateParamsPaymentMethodOptionCardInstallmentPlan.type`, `ConfirmationToken.PaymentMethodOption.Card.Installment.Plan.type`, `Invoice.CreateParamsPaymentSettingPaymentMethodOptionCardInstallmentPlan.type`, `Invoice.ModifyParamsPaymentSettingPaymentMethodOptionCardInstallmentPlan.type`, `PaymentIntent.ConfirmParamsPaymentMethodOptionCardInstallmentPlan.type`, `PaymentIntent.CreateParamsPaymentMethodOptionCardInstallmentPlan.type`, `PaymentIntent.ModifyParamsPaymentMethodOptionCardInstallmentPlan.type`, `PaymentIntent.PaymentMethodOption.Card.Installment.AvailablePlan.type`, and `PaymentIntent.PaymentMethodOption.Card.Installment.Plan.type` from `literal('fixed_count')` to `enum('bonus'|'fixed_count'|'revolving')`\n* Add support for new value `buut` on enums `Charge.PaymentMethodDetail.Ideal.bank`, `ConfirmationToken.CreateParamsPaymentMethodDatumIdeal.bank`, `ConfirmationToken.PaymentMethodPreview.Ideal.bank`, `PaymentIntent.ConfirmParamsPaymentMethodDatumIdeal.bank`, `PaymentIntent.CreateParamsPaymentMethodDatumIdeal.bank`, `PaymentIntent.ModifyParamsPaymentMethodDatumIdeal.bank`, `PaymentMethod.CreateParamsIdeal.bank`, `PaymentMethod.Ideal.bank`, `SetupAttempt.PaymentMethodDetail.Ideal.bank`, `SetupIntent.ConfirmParamsPaymentMethodDatumIdeal.bank`, `SetupIntent.CreateParamsPaymentMethodDatumIdeal.bank`, and `SetupIntent.ModifyParamsPaymentMethodDatumIdeal.bank`\n* Add support for new value `BUUTNL2A` on enums `Charge.PaymentMethodDetail.Ideal.bic`, `ConfirmationToken.PaymentMethodPreview.Ideal.bic`, `PaymentMethod.Ideal.bic`, and `SetupAttempt.PaymentMethodDetail.Ideal.bic`\n* Add support for `subscriptions` on `PaymentIntent.ConfirmParamsPaymentMethodOptionKlarna`, `PaymentIntent.CreateParamsPaymentMethodOptionKlarna`, `PaymentIntent.ModifyParamsPaymentMethodOptionKlarna`, and `checkout.Session.CreateParamsPaymentMethodOptionKlarna`\n* Add support for new value `crypto` on enum `checkout.Session.CreateParams.payment_method_types`\n* Add support for `billing_mode` on `Invoice.CreatePreviewParamsScheduleDetail`, `Invoice.CreatePreviewParamsSubscriptionDetail`, `Quote.CreateParamsSubscriptionDatum`, `Quote.SubscriptionDatum`, `Subscription.CreateParams`, `SubscriptionSchedule.CreateParams`, `SubscriptionSchedule`, `Subscription`, and `checkout.Session.CreateParamsSubscriptionDatum`\n* Add support for new value `crypto` on enums `ConfirmationToken.CreateParamsPaymentMethodDatum.type`, `PaymentIntent.ConfirmParamsPaymentMethodDatum.type`, `PaymentIntent.CreateParamsPaymentMethodDatum.type`, `PaymentIntent.ModifyParamsPaymentMethodDatum.type`, `SetupIntent.ConfirmParamsPaymentMethodDatum.type`, `SetupIntent.CreateParamsPaymentMethodDatum.type`, and `SetupIntent.ModifyParamsPaymentMethodDatum.type`\n* Add support for new value `crypto` on enums `ConfirmationToken.PaymentMethodPreview.type` and `PaymentMethod.type`\n* Add support for new value `crypto` on enums `Customer.ListPaymentMethodsParams.type`, `PaymentMethod.CreateParams.type`, and `PaymentMethod.ListParams.type`\n* Change type of `Dispute.enhanced_eligibility_types` from `literal('visa_compelling_evidence_3')` to `enum('visa_compelling_evidence_3'|'visa_compliance')`\n* Add support for new value `compliance` on enum `Dispute.PaymentMethodDetail.Card.case_type`\n* Add support for new value `terminal.reader.action_updated` on enum `Event.type`\n* Add support for `related_person` on `Identity.VerificationSession` and `identity.VerificationSession.CreateParams`\n* Add support for `matching` on `Identity.VerificationSession.Option`\n* Add support for new value `crypto` on enums `Invoice.CreateParamsPaymentSetting.payment_method_types`, `Invoice.ModifyParamsPaymentSetting.payment_method_types`, `Invoice.PaymentSetting.payment_method_types`, `Subscription.CreateParamsPaymentSetting.payment_method_types`, `Subscription.ModifyParamsPaymentSetting.payment_method_types`, and `Subscription.PaymentSetting.payment_method_types`\n* Add support for `klarna` on `Mandate.PaymentMethodDetail`, `SetupIntent.ConfirmParamsPaymentMethodOption`, `SetupIntent.CreateParamsPaymentMethodOption`, `SetupIntent.ModifyParamsPaymentMethodOption`, and `SetupIntent.PaymentMethodOption`\n* Add support for `on_demand` on `PaymentIntent.ConfirmParamsPaymentMethodOptionKlarna`, `PaymentIntent.CreateParamsPaymentMethodOptionKlarna`, and `PaymentIntent.ModifyParamsPaymentMethodOptionKlarna`\n* Change type of `PaymentIntent.ConfirmParamsPaymentMethodOptionKlarna.setup_future_usage`, `PaymentIntent.CreateParamsPaymentMethodOptionKlarna.setup_future_usage`, `PaymentIntent.ModifyParamsPaymentMethodOptionKlarna.setup_future_usage`, and `PaymentIntent.PaymentMethodOption.Klarna.setup_future_usage` from `literal('none')` to `enum('none'|'off_session'|'on_session')`\n* Add support for `ua` on `Tax.Registration.CountryOption` and `tax.Registration.CreateParamsCountryOption`\n* Change type of `terminal.Location.ModifyParams.display_name` from `string` to `emptyable(string)`\n* Add support for `collect_payment_method` and `confirm_payment_intent` on `Terminal.Reader.Action`\n* Add support for new values `collect_payment_method` and `confirm_payment_intent` on enum `Terminal.Reader.Action.type`\n* Add support for `status` on `treasury.FinancialAccount.ListParams`\n* Add support for new value `terminal.reader.action_updated` on enums `WebhookEndpoint.CreateParams.enabled_events` and `WebhookEndpoint.ModifyParams.enabled_events`\n* Add support for new value `2025-06-30.basil` on enum `WebhookEndpoint.CreateParams.api_version`\n* Add support for snapshot event `terminal.reader.action_updated` with resource `terminal.Reader`\n", "created_at": "2025-06-06T18:41:03Z", "updated_at": "2025-07-20T20:52:36Z", "closed_at": "2025-07-01T20:07:26Z", "merged_at": "2025-07-01T20:07:26Z", "merge_commit_sha": "1b3c54c50387eb2085b4e91fb44273d655770ab4", "assignee": null, "assignees": [], "requested_reviewers": [], "requested_teams": [], "labels": [], "milestone": null, "draft": false, "commits_url": "https://api.github.com/repos/stripe/stripe-python/pulls/1526/commits", "review_comments_url": "https://api.github.com/repos/stripe/stripe-python/pulls/1526/comments", "review_comment_url": "https://api.github.com/repos/stripe/stripe-python/pulls/comments{/number}", "comments_url": "https://api.github.com/repos/stripe/stripe-python/issues/1526/comments", "statuses_url": "https://api.github.com/repos/stripe/stripe-python/statuses/2e47c1ec9a9c73c88be6d3387185360324adea76", "head": {"label": "stripe:latest-codegen-master", "ref": "latest-codegen-master", "sha": "2e47c1ec9a9c73c88be6d3387185360324adea76", "user": {"login": "stripe", "id": 856813, "node_id": "MDEyOk9yZ2FuaXphdGlvbjg1NjgxMw==", "avatar_url": "https://avatars.githubusercontent.com/u/856813?v=4", "gravatar_id": "", "url": "https://api.github.com/users/stripe", "html_url": "https://github.com/stripe", "followers_url": "https://api.github.com/users/stripe/followers", "following_url": "https://api.github.com/users/stripe/following{/other_user}", "gists_url": "https://api.github.com/users/stripe/gists{/gist_id}", "starred_url": "https://api.github.com/users/stripe/starred{/owner}{/repo}", "subscriptions_url": "https://api.github.com/users/stripe/subscriptions", "organizations_url": "https://api.github.com/users/stripe/orgs", "repos_url": "https://api.github.com/users/stripe/repos", "events_url": "https://api.github.com/users/stripe/events{/privacy}", "received_events_url": "https://api.github.com/users/stripe/received_events", "type": "Organization", "user_view_type": "public", "site_admin": false}, "repo": {"id": 1953389, "node_id": "MDEwOlJlcG9zaXRvcnkxOTUzMzg5", "name": "stripe-python", "full_name": "stripe/stripe-python", "private": false, "owner": {"login": "stripe", "id": 856813, "node_id": "MDEyOk9yZ2FuaXphdGlvbjg1NjgxMw==", "avatar_url": "https://avatars.githubusercontent.com/u/856813?v=4", "gravatar_id": "", "url": "https://api.github.com/users/stripe", "html_url": "https://github.com/stripe", "followers_url": "https://api.github.com/users/stripe/followers", "following_url": "https://api.github.com/users/stripe/following{/other_user}", "gists_url": "https://api.github.com/users/stripe/gists{/gist_id}", "starred_url": "https://api.github.com/users/stripe/starred{/owner}{/repo}", "subscriptions_url": "https://api.github.com/users/stripe/subscriptions", "organizations_url": "https://api.github.com/users/stripe/orgs", "repos_url": "https://api.github.com/users/stripe/repos", "events_url": "https://api.github.com/users/stripe/events{/privacy}", "received_events_url": "https://api.github.com/users/stripe/received_events", "type": "Organization", "user_view_type": "public", "site_admin": false}, "html_url": "https://github.com/stripe/stripe-python", "description": "Python library for the Stripe API.    ", "fork": false, "url": "https://api.github.com/repos/stripe/stripe-python", "forks_url": "https://api.github.com/repos/stripe/stripe-python/forks", "keys_url": "https://api.github.com/repos/stripe/stripe-python/keys{/key_id}", "collaborators_url": "https://api.github.com/repos/stripe/stripe-python/collaborators{/collaborator}", "teams_url": "https://api.github.com/repos/stripe/stripe-python/teams", "hooks_url": "https://api.github.com/repos/stripe/stripe-python/hooks", "issue_events_url": "https://api.github.com/repos/stripe/stripe-python/issues/events{/number}", "events_url": "https://api.github.com/repos/stripe/stripe-python/events", "assignees_url": "https://api.github.com/repos/stripe/stripe-python/assignees{/user}", "branches_url": "https://api.github.com/repos/stripe/stripe-python/branches{/branch}", "tags_url": "https://api.github.com/repos/stripe/stripe-python/tags", "blobs_url": "https://api.github.com/repos/stripe/stripe-python/git/blobs{/sha}", "git_tags_url": "https://api.github.com/repos/stripe/stripe-python/git/tags{/sha}", "git_refs_url": "https://api.github.com/repos/stripe/stripe-python/git/refs{/sha}", "trees_url": "https://api.github.com/repos/stripe/stripe-python/git/trees{/sha}", "statuses_url": "https://api.github.com/repos/stripe/stripe-python/statuses/{sha}", "languages_url": "https://api.github.com/repos/stripe/stripe-python/languages", "stargazers_url": "https://api.github.com/repos/stripe/stripe-python/stargazers", "contributors_url": "https://api.github.com/repos/stripe/stripe-python/contributors", "subscribers_url": "https://api.github.com/repos/stripe/stripe-python/subscribers", "subscription_url": "https://api.github.com/repos/stripe/stripe-python/subscription", "commits_url": "https://api.github.com/repos/stripe/stripe-python/commits{/sha}", "git_commits_url": "https://api.github.com/repos/stripe/stripe-python/git/commits{/sha}", "comments_url": "https://api.github.com/repos/stripe/stripe-python/comments{/number}", "issue_comment_url": "https://api.github.com/repos/stripe/stripe-python/issues/comments{/number}", "contents_url": "https://api.github.com/repos/stripe/stripe-python/contents/{+path}", "compare_url": "https://api.github.com/repos/stripe/stripe-python/compare/{base}...{head}", "merges_url": "https://api.github.com/repos/stripe/stripe-python/merges", "archive_url": "https://api.github.com/repos/stripe/stripe-python/{archive_format}{/ref}", "downloads_url": "https://api.github.com/repos/stripe/stripe-python/downloads", "issues_url": "https://api.github.com/repos/stripe/stripe-python/issues{/number}", "pulls_url": "https://api.github.com/repos/stripe/stripe-python/pulls{/number}", "milestones_url": "https://api.github.com/repos/stripe/stripe-python/milestones{/number}", "notifications_url": "https://api.github.com/repos/stripe/stripe-python/notifications{?since,all,participating}", "labels_url": "https://api.github.com/repos/stripe/stripe-python/labels{/name}", "releases_url": "https://api.github.com/repos/stripe/stripe-python/releases{/id}", "deployments_url": "https://api.github.com/repos/stripe/stripe-python/deployments", "created_at": "2011-06-25T19:53:04Z", "updated_at": "2026-01-17T16:02:23Z", "pushed_at": "2026-01-19T00:25:01Z", "git_url": "git://github.com/stripe/stripe-python.git", "ssh_url": "org-856813@github.com:stripe/stripe-python.git", "clone_url": "https://github.com/stripe/stripe-python.git", "svn_url": "https://github.com/stripe/stripe-python", "homepage": "https://stripe.com", "size": 28946, "stargazers_count": 1941, "watchers_count": 1941, "language": "Python", "has_issues": true, "has_projects": false, "has_downloads": true, "has_wiki": true, "has_pages": false, "has_discussions": false, "forks_count": 484, "mirror_url": null, "archived": false, "disabled": false, "open_issues_count": 20, "license": {"key": "mit", "name": "MIT License", "spdx_id": "MIT", "url": "https://api.github.com/licenses/mit", "node_id": "MDc6TGljZW5zZTEz"}, "allow_forking": true, "is_template": false, "web_commit_signoff_required": false, "topics": ["stripe", "stripe-sdk"], "visibility": "public", "forks": 484, "open_issues": 20, "watchers": 1941, "default_branch": "master"}}, "base": {"label": "stripe:master", "ref": "master", "sha": "42c1bd0ee254e345bd778b6bc949299acf633d05", "user": {"login": "stripe", "id": 856813, "node_id": "MDEyOk9yZ2FuaXphdGlvbjg1NjgxMw==", "avatar_url": "https://avatars.githubusercontent.com/u/856813?v=4", "gravatar_id": "", "url": "https://api.github.com/users/stripe", "html_url": "https://github.com/stripe", "followers_url": "https://api.github.com/users/stripe/followers", "following_url": "https://api.github.com/users/stripe/following{/other_user}", "gists_url": "https://api.github.com/users/stripe/gists{/gist_id}", "starred_url": "https://api.github.com/users/stripe/starred{/owner}{/repo}", "subscriptions_url": "https://api.github.com/users/stripe/subscriptions", "organizations_url": "https://api.github.com/users/stripe/orgs", "repos_url": "https://api.github.com/users/stripe/repos", "events_url": "https://api.github.com/users/stripe/events{/privacy}", "received_events_url": "https://api.github.com/users/stripe/received_events", "type": "Organization", "user_view_type": "public", "site_admin": false}, "repo": {"id": 1953389, "node_id": "MDEwOlJlcG9zaXRvcnkxOTUzMzg5", "name": "stripe-python", "full_name": "stripe/stripe-python", "private": false, "owner": {"login": "stripe", "id": 856813, "node_id": "MDEyOk9yZ2FuaXphdGlvbjg1NjgxMw==", "avatar_url": "https://avatars.githubusercontent.com/u/856813?v=4", "gravatar_id": "", "url": "https://api.github.com/users/stripe", "html_url": "https://github.com/stripe", "followers_url": "https://api.github.com/users/stripe/followers", "following_url": "https://api.github.com/users/stripe/following{/other_user}", "gists_url": "https://api.github.com/users/stripe/gists{/gist_id}", "starred_url": "https://api.github.com/users/stripe/starred{/owner}{/repo}", "subscriptions_url": "https://api.github.com/users/stripe/subscriptions", "organizations_url": "https://api.github.com/users/stripe/orgs", "repos_url": "https://api.github.com/users/stripe/repos", "events_url": "https://api.github.com/users/stripe/events{/privacy}", "received_events_url": "https://api.github.com/users/stripe/received_events", "type": "Organization", "user_view_type": "public", "site_admin": false}, "html_url": "https://github.com/stripe/stripe-python", "description": "Python library for the Stripe API.    ", "fork": false, "url": "https://api.github.com/repos/stripe/stripe-python", "forks_url": "https://api.github.com/repos/stripe/stripe-python/forks", "keys_url": "https://api.github.com/repos/stripe/stripe-python/keys{/key_id}", "collaborators_url": "https://api.github.com/repos/stripe/stripe-python/collaborators{/collaborator}", "teams_url": "https://api.github.com/repos/stripe/stripe-python/teams", "hooks_url": "https://api.github.com/repos/stripe/stripe-python/hooks", "issue_events_url": "https://api.github.com/repos/stripe/stripe-python/issues/events{/number}", "events_url": "https://api.github.com/repos/stripe/stripe-python/events", "assignees_url": "https://api.github.com/repos/stripe/stripe-python/assignees{/user}", "branches_url": "https://api.github.com/repos/stripe/stripe-python/branches{/branch}", "tags_url": "https://api.github.com/repos/stripe/stripe-python/tags", "blobs_url": "https://api.github.com/repos/stripe/stripe-python/git/blobs{/sha}", "git_tags_url": "https://api.github.com/repos/stripe/stripe-python/git/tags{/sha}", "git_refs_url": "https://api.github.com/repos/stripe/stripe-python/git/refs{/sha}", "trees_url": "https://api.github.com/repos/stripe/stripe-python/git/trees{/sha}", "statuses_url": "https://api.github.com/repos/stripe/stripe-python/statuses/{sha}", "languages_url": "https://api.github.com/repos/stripe/stripe-python/languages", "stargazers_url": "https://api.github.com/repos/stripe/stripe-python/stargazers", "contributors_url": "https://api.github.com/repos/stripe/stripe-python/contributors", "subscribers_url": "https://api.github.com/repos/stripe/stripe-python/subscribers", "subscription_url": "https://api.github.com/repos/stripe/stripe-python/subscription", "commits_url": "https://api.github.com/repos/stripe/stripe-python/commits{/sha}", "git_commits_url": "https://api.github.com/repos/stripe/stripe-python/git/commits{/sha}", "comments_url": "https://api.github.com/repos/stripe/stripe-python/comments{/number}", "issue_comment_url": "https://api.github.com/repos/stripe/stripe-python/issues/comments{/number}", "contents_url": "https://api.github.com/repos/stripe/stripe-python/contents/{+path}", "compare_url": "https://api.github.com/repos/stripe/stripe-python/compare/{base}...{head}", "merges_url": "https://api.github.com/repos/stripe/stripe-python/merges", "archive_url": "https://api.github.com/repos/stripe/stripe-python/{archive_format}{/ref}", "downloads_url": "https://api.github.com/repos/stripe/stripe-python/downloads", "issues_url": "https://api.github.com/repos/stripe/stripe-python/issues{/number}", "pulls_url": "https://api.github.com/repos/stripe/stripe-python/pulls{/number}", "milestones_url": "https://api.github.com/repos/stripe/stripe-python/milestones{/number}", "notifications_url": "https://api.github.com/repos/stripe/stripe-python/notifications{?since,all,participating}", "labels_url": "https://api.github.com/repos/stripe/stripe-python/labels{/name}", "releases_url": "https://api.github.com/repos/stripe/stripe-python/releases{/id}", "deployments_url": "https://api.github.com/repos/stripe/stripe-python/deployments", "created_at": "2011-06-25T19:53:04Z", "updated_at": "2026-01-17T16:02:23Z", "pushed_at": "2026-01-19T00:25:01Z", "git_url": "git://github.com/stripe/stripe-python.git", "ssh_url": "org-856813@github.com:stripe/stripe-python.git", "clone_url": "https://github.com/stripe/stripe-python.git", "svn_url": "https://github.com/stripe/stripe-python", "homepage": "https://stripe.com", "size": 28946, "stargazers_count": 1941, "watchers_count": 1941, "language": "Python", "has_issues": true, "has_projects": false, "has_downloads": true, "has_wiki": true, "has_pages": false, "has_discussions": false, "forks_count": 484, "mirror_url": null, "archived": false, "disabled": false, "open_issues_count": 20, "license": {"key": "mit", "name": "MIT License", "spdx_id": "MIT", "url": "https://api.github.com/licenses/mit", "node_id": "MDc6TGljZW5zZTEz"}, "allow_forking": true, "is_template": false, "web_commit_signoff_required": false, "topics": ["stripe", "stripe-sdk"], "visibility": "public", "forks": 484, "open_issues": 20, "watchers": 1941, "default_branch": "master"}}, "_links": {"self": {"href": "https://api.github.com/repos/stripe/stripe-python/pulls/1526"}, "html": {"href": "https://github.com/stripe/stripe-python/pull/1526"}, "issue": {"href": "https://api.github.com/repos/stripe/stripe-python/issues/1526"}, "comments": {"href": "https://api.github.com/repos/stripe/stripe-python/issues/1526/comments"}, "review_comments": {"href": "https://api.github.com/repos/stripe/stripe-python/pulls/1526/comments"}, "review_comment": {"href": "https://api.github.com/repos/stripe/stripe-python/pulls/comments{/number}"}, "commits": {"href": "https://api.github.com/repos/stripe/stripe-python/pulls/1526/commits"}, "statuses": {"href": "https://api.github.com/repos/stripe/stripe-python/statuses/2e47c1ec9a9c73c88be6d3387185360324adea76"}}, "author_association": "CONTRIBUTOR", "auto_merge": {"enabled_by": {"login": "stripe-openapi[bot]", "id": 105521251, "node_id": "BOT_kgDOBkogYw", "avatar_url": "https://avatars.githubusercontent.com/in/200680?v=4", "gravatar_id": "", "url": "https://api.github.com/users/stripe-openapi%5Bbot%5D", "html_url": "https://github.com/apps/stripe-openapi", "followers_url": "https://api.github.com/users/stripe-openapi%5Bbot%5D/followers", "following_url": "https://api.github.com/users/stripe-openapi%5Bbot%5D/following{/other_user}", "gists_url": "https://api.github.com/users/stripe-openapi%5Bbot%5D/gists{/gist_id}", "starred_url": "https://api.github.com/users/stripe-openapi%5Bbot%5D/starred{/owner}{/repo}", "subscriptions_url": "https://api.github.com/users/stripe-openapi%5Bbot%5D/subscriptions", "organizations_url": "https://api.github.com/users/stripe-openapi%5Bbot%5D/orgs", "repos_url": "https://api.github.com/users/stripe-openapi%5Bbot%5D/repos", "events_url": "https://api.github.com/users/stripe-openapi%5Bbot%5D/events{/privacy}", "received_events_url": "https://api.github.com/users/stripe-openapi%5Bbot%5D/received_events", "type": "Bot", "user_view_type": "public", "site_admin": false}, "merge_method": "squash", "commit_title": null, "commit_message": null}, "active_lock_reason": null, "merged": true, "mergeable": null, "rebaseable": null, "mergeable_state": "unknown", "merged_by": {"login": "stripe-openapi[bot]", "id": 105521251, "node_id": "BOT_kgDOBkogYw", "avatar_url": "https://avatars.githubusercontent.com/in/200680?v=4", "gravatar_id": "", "url": "https://api.github.com/users/stripe-openapi%5Bbot%5D", "html_url": "https://github.com/apps/stripe-openapi", "followers_url": "https://api.github.com/users/stripe-openapi%5Bbot%5D/followers", "following_url": "https://api.github.com/users/stripe-openapi%5Bbot%5D/following{/other_user}", "gists_url": "https://api.github.com/users/stripe-openapi%5Bbot%5D/gists{/gist_id}", "starred_url": "https://api.github.com/users/stripe-openapi%5Bbot%5D/starred{/owner}{/repo}", "subscriptions_url": "https://api.github.com/users/stripe-openapi%5Bbot%5D/subscriptions", "organizations_url": "https://api.github.com/users/stripe-openapi%5Bbot%5D/orgs", "repos_url": "https://api.github.com/users/stripe-openapi%5Bbot%5D/repos", "events_url": "https://api.github.com/users/stripe-openapi%5Bbot%5D/events{/privacy}", "received_events_url": "https://api.github.com/users/stripe-openapi%5Bbot%5D/received_events", "type": "Bot", "user_view_type": "public", "site_admin": false}, "comments": 0, "review_comments": 0, "maintainer_can_modify": false, "commits": 10, "additions": 3360, "deletions": 583, "changed_files": 79}