{"url": "https://api.github.com/repos/stripe/stripe-python/pulls/1103", "id": 1575149240, "node_id": "PR_kwDOAB3Obc5d4t64", "html_url": "https://github.com/stripe/stripe-python/pull/1103", "diff_url": "https://github.com/stripe/stripe-python/pull/1103.diff", "patch_url": "https://github.com/stripe/stripe-python/pull/1103.patch", "issue_url": "https://api.github.com/repos/stripe/stripe-python/issues/1103", "number": 1103, "state": "closed", "locked": false, "title": "Inner resource classes", "user": {"login": "richardm-stripe", "id": 52928443, "node_id": "MDQ6VXNlcjUyOTI4NDQz", "avatar_url": "https://avatars.githubusercontent.com/u/52928443?v=4", "gravatar_id": "", "url": "https://api.github.com/users/richardm-stripe", "html_url": "https://github.com/richardm-stripe", "followers_url": "https://api.github.com/users/richardm-stripe/followers", "following_url": "https://api.github.com/users/richardm-stripe/following{/other_user}", "gists_url": "https://api.github.com/users/richardm-stripe/gists{/gist_id}", "starred_url": "https://api.github.com/users/richardm-stripe/starred{/owner}{/repo}", "subscriptions_url": "https://api.github.com/users/richardm-stripe/subscriptions", "organizations_url": "https://api.github.com/users/richardm-stripe/orgs", "repos_url": "https://api.github.com/users/richardm-stripe/repos", "events_url": "https://api.github.com/users/richardm-stripe/events{/privacy}", "received_events_url": "https://api.github.com/users/richardm-stripe/received_events", "type": "User", "user_view_type": "public", "site_admin": false}, "body": "\r\n## Summary\r\n\r\nLike https://github.com/stripe/stripe-python/pull/1061, but merging into master now.\r\n\r\nReplaces StripeObject types on resource classes with more granular classes that define the specific fields that can be accessed.\r\n\r\nThis is not just a type annotation change. We also change the deserialization code in StripeObject.refresh_from and util.convert_to_stripe_object so, in order that the type annotations tell the truth, at runtime, these StripeObject classes will be instances of the more specific classes that are children of StripeObject.\r\n\r\nWe don't consider changing objects to a more specific subclass to be a breaking change, however, it's possible that any code that uses type(...) == StripeObject instead of instanceof(StripeObject, ...), or does similar introspection, will be affected by this change,\r\n\r\nInto beta for now.\r\n\r\nNote: There is a very obscure breaking change here: PromotionCode.restrictions.currency_options will now be of type dict instead of StripeObject.", "created_at": "2023-10-26T16:03:57Z", "updated_at": "2023-10-27T01:53:14Z", "closed_at": "2023-10-26T16:29:48Z", "merged_at": "2023-10-26T16:29:48Z", "merge_commit_sha": "4fe269b0fb463695170d3b3d4b8964b9ebfafe64", "assignee": null, "assignees": [], "requested_reviewers": [], "requested_teams": [], "labels": [], "milestone": null, "draft": false, "commits_url": "https://api.github.com/repos/stripe/stripe-python/pulls/1103/commits", "review_comments_url": "https://api.github.com/repos/stripe/stripe-python/pulls/1103/comments", "review_comment_url": "https://api.github.com/repos/stripe/stripe-python/pulls/comments{/number}", "comments_url": "https://api.github.com/repos/stripe/stripe-python/issues/1103/comments", "statuses_url": "https://api.github.com/repos/stripe/stripe-python/statuses/1d3498cac13d188af8882b0776a22ffdb4e84f57", "head": {"label": "stripe:richardm-inner-resource-types", "ref": "richardm-inner-resource-types", "sha": "1d3498cac13d188af8882b0776a22ffdb4e84f57", "user": {"login": "stripe", "id": 856813, "node_id": "MDEyOk9yZ2FuaXphdGlvbjg1NjgxMw==", "avatar_url": "https://avatars.githubusercontent.com/u/856813?v=4", "gravatar_id": "", "url": "https://api.github.com/users/stripe", "html_url": "https://github.com/stripe", "followers_url": "https://api.github.com/users/stripe/followers", "following_url": "https://api.github.com/users/stripe/following{/other_user}", "gists_url": "https://api.github.com/users/stripe/gists{/gist_id}", "starred_url": "https://api.github.com/users/stripe/starred{/owner}{/repo}", "subscriptions_url": "https://api.github.com/users/stripe/subscriptions", "organizations_url": "https://api.github.com/users/stripe/orgs", "repos_url": "https://api.github.com/users/stripe/repos", "events_url": "https://api.github.com/users/stripe/events{/privacy}", "received_events_url": "https://api.github.com/users/stripe/received_events", "type": "Organization", "user_view_type": "public", "site_admin": false}, "repo": {"id": 1953389, "node_id": "MDEwOlJlcG9zaXRvcnkxOTUzMzg5", "name": "stripe-python", "full_name": "stripe/stripe-python", "private": false, "owner": {"login": "stripe", "id": 856813, "node_id": "MDEyOk9yZ2FuaXphdGlvbjg1NjgxMw==", "avatar_url": "https://avatars.githubusercontent.com/u/856813?v=4", "gravatar_id": "", "url": "https://api.github.com/users/stripe", "html_url": "https://github.com/stripe", "followers_url": "https://api.github.com/users/stripe/followers", "following_url": "https://api.github.com/users/stripe/following{/other_user}", "gists_url": "https://api.github.com/users/stripe/gists{/gist_id}", "starred_url": "https://api.github.com/users/stripe/starred{/owner}{/repo}", "subscriptions_url": "https://api.github.com/users/stripe/subscriptions", "organizations_url": "https://api.github.com/users/stripe/orgs", "repos_url": "https://api.github.com/users/stripe/repos", "events_url": "https://api.github.com/users/stripe/events{/privacy}", "received_events_url": "https://api.github.com/users/stripe/received_events", "type": "Organization", "user_view_type": "public", "site_admin": false}, "html_url": "https://github.com/stripe/stripe-python", "description": "Python library for the Stripe API.    ", "fork": false, "url": "https://api.github.com/repos/stripe/stripe-python", "forks_url": "https://api.github.com/repos/stripe/stripe-python/forks", "keys_url": "https://api.github.com/repos/stripe/stripe-python/keys{/key_id}", "collaborators_url": "https://api.github.com/repos/stripe/stripe-python/collaborators{/collaborator}", "teams_url": "https://api.github.com/repos/stripe/stripe-python/teams", "hooks_url": "https://api.github.com/repos/stripe/stripe-python/hooks", "issue_events_url": "https://api.github.com/repos/stripe/stripe-python/issues/events{/number}", "events_url": "https://api.github.com/repos/stripe/stripe-python/events", "assignees_url": "https://api.github.com/repos/stripe/stripe-python/assignees{/user}", "branches_url": "https://api.github.com/repos/stripe/stripe-python/branches{/branch}", "tags_url": "https://api.github.com/repos/stripe/stripe-python/tags", "blobs_url": "https://api.github.com/repos/stripe/stripe-python/git/blobs{/sha}", "git_tags_url": "https://api.github.com/repos/stripe/stripe-python/git/tags{/sha}", "git_refs_url": "https://api.github.com/repos/stripe/stripe-python/git/refs{/sha}", "trees_url": "https://api.github.com/repos/stripe/stripe-python/git/trees{/sha}", "statuses_url": "https://api.github.com/repos/stripe/stripe-python/statuses/{sha}", "languages_url": "https://api.github.com/repos/stripe/stripe-python/languages", "stargazers_url": "https://api.github.com/repos/stripe/stripe-python/stargazers", "contributors_url": "https://api.github.com/repos/stripe/stripe-python/contributors", "subscribers_url": "https://api.github.com/repos/stripe/stripe-python/subscribers", "subscription_url": "https://api.github.com/repos/stripe/stripe-python/subscription", "commits_url": "https://api.github.com/repos/stripe/stripe-python/commits{/sha}", "git_commits_url": "https://api.github.com/repos/stripe/stripe-python/git/commits{/sha}", "comments_url": "https://api.github.com/repos/stripe/stripe-python/comments{/number}", "issue_comment_url": "https://api.github.com/repos/stripe/stripe-python/issues/comments{/number}", "contents_url": "https://api.github.com/repos/stripe/stripe-python/contents/{+path}", "compare_url": "https://api.github.com/repos/stripe/stripe-python/compare/{base}...{head}", "merges_url": "https://api.github.com/repos/stripe/stripe-python/merges", "archive_url": "https://api.github.com/repos/stripe/stripe-python/{archive_format}{/ref}", "downloads_url": "https://api.github.com/repos/stripe/stripe-python/downloads", "issues_url": "https://api.github.com/repos/stripe/stripe-python/issues{/number}", "pulls_url": "https://api.github.com/repos/stripe/stripe-python/pulls{/number}", "milestones_url": "https://api.github.com/repos/stripe/stripe-python/milestones{/number}", "notifications_url": "https://api.github.com/repos/stripe/stripe-python/notifications{?since,all,participating}", "labels_url": "https://api.github.com/repos/stripe/stripe-python/labels{/name}", "releases_url": "https://api.github.com/repos/stripe/stripe-python/releases{/id}", "deployments_url": "https://api.github.com/repos/stripe/stripe-python/deployments", "created_at": "2011-06-25T19:53:04Z", "updated_at": "2026-01-17T16:02:23Z", "pushed_at": "2026-01-19T00:25:01Z", "git_url": "git://github.com/stripe/stripe-python.git", "ssh_url": "org-856813@github.com:stripe/stripe-python.git", "clone_url": "https://github.com/stripe/stripe-python.git", "svn_url": "https://github.com/stripe/stripe-python", "homepage": "https://stripe.com", "size": 28946, "stargazers_count": 1941, "watchers_count": 1941, "language": "Python", "has_issues": true, "has_projects": false, "has_downloads": true, "has_wiki": true, "has_pages": false, "has_discussions": false, "forks_count": 484, "mirror_url": null, "archived": false, "disabled": false, "open_issues_count": 20, "license": {"key": "mit", "name": "MIT License", "spdx_id": "MIT", "url": "https://api.github.com/licenses/mit", "node_id": "MDc6TGljZW5zZTEz"}, "allow_forking": true, "is_template": false, "web_commit_signoff_required": false, "topics": ["stripe", "stripe-sdk"], "visibility": "public", "forks": 484, "open_issues": 20, "watchers": 1941, "default_branch": "master"}}, "base": {"label": "stripe:master", "ref": "master", "sha": "af8e5f190f1c0029fb8da2a86c2e8661341fac16", "user": {"login": "stripe", "id": 856813, "node_id": "MDEyOk9yZ2FuaXphdGlvbjg1NjgxMw==", "avatar_url": "https://avatars.githubusercontent.com/u/856813?v=4", "gravatar_id": "", "url": "https://api.github.com/users/stripe", "html_url": "https://github.com/stripe", "followers_url": "https://api.github.com/users/stripe/followers", "following_url": "https://api.github.com/users/stripe/following{/other_user}", "gists_url": "https://api.github.com/users/stripe/gists{/gist_id}", "starred_url": "https://api.github.com/users/stripe/starred{/owner}{/repo}", "subscriptions_url": "https://api.github.com/users/stripe/subscriptions", "organizations_url": "https://api.github.com/users/stripe/orgs", "repos_url": "https://api.github.com/users/stripe/repos", "events_url": "https://api.github.com/users/stripe/events{/privacy}", "received_events_url": "https://api.github.com/users/stripe/received_events", "type": "Organization", "user_view_type": "public", "site_admin": false}, "repo": {"id": 1953389, "node_id": "MDEwOlJlcG9zaXRvcnkxOTUzMzg5", "name": "stripe-python", "full_name": "stripe/stripe-python", "private": false, "owner": {"login": "stripe", "id": 856813, "node_id": "MDEyOk9yZ2FuaXphdGlvbjg1NjgxMw==", "avatar_url": "https://avatars.githubusercontent.com/u/856813?v=4", "gravatar_id": "", "url": "https://api.github.com/users/stripe", "html_url": "https://github.com/stripe", "followers_url": "https://api.github.com/users/stripe/followers", "following_url": "https://api.github.com/users/stripe/following{/other_user}", "gists_url": "https://api.github.com/users/stripe/gists{/gist_id}", "starred_url": "https://api.github.com/users/stripe/starred{/owner}{/repo}", "subscriptions_url": "https://api.github.com/users/stripe/subscriptions", "organizations_url": "https://api.github.com/users/stripe/orgs", "repos_url": "https://api.github.com/users/stripe/repos", "events_url": "https://api.github.com/users/stripe/events{/privacy}", "received_events_url": "https://api.github.com/users/stripe/received_events", "type": "Organization", "user_view_type": "public", "site_admin": false}, "html_url": "https://github.com/stripe/stripe-python", "description": "Python library for the Stripe API.    ", "fork": false, "url": "https://api.github.com/repos/stripe/stripe-python", "forks_url": "https://api.github.com/repos/stripe/stripe-python/forks", "keys_url": "https://api.github.com/repos/stripe/stripe-python/keys{/key_id}", "collaborators_url": "https://api.github.com/repos/stripe/stripe-python/collaborators{/collaborator}", "teams_url": "https://api.github.com/repos/stripe/stripe-python/teams", "hooks_url": "https://api.github.com/repos/stripe/stripe-python/hooks", "issue_events_url": "https://api.github.com/repos/stripe/stripe-python/issues/events{/number}", "events_url": "https://api.github.com/repos/stripe/stripe-python/events", "assignees_url": "https://api.github.com/repos/stripe/stripe-python/assignees{/user}", "branches_url": "https://api.github.com/repos/stripe/stripe-python/branches{/branch}", "tags_url": "https://api.github.com/repos/stripe/stripe-python/tags", "blobs_url": "https://api.github.com/repos/stripe/stripe-python/git/blobs{/sha}", "git_tags_url": "https://api.github.com/repos/stripe/stripe-python/git/tags{/sha}", "git_refs_url": "https://api.github.com/repos/stripe/stripe-python/git/refs{/sha}", "trees_url": "https://api.github.com/repos/stripe/stripe-python/git/trees{/sha}", "statuses_url": "https://api.github.com/repos/stripe/stripe-python/statuses/{sha}", "languages_url": "https://api.github.com/repos/stripe/stripe-python/languages", "stargazers_url": "https://api.github.com/repos/stripe/stripe-python/stargazers", "contributors_url": "https://api.github.com/repos/stripe/stripe-python/contributors", "subscribers_url": "https://api.github.com/repos/stripe/stripe-python/subscribers", "subscription_url": "https://api.github.com/repos/stripe/stripe-python/subscription", "commits_url": "https://api.github.com/repos/stripe/stripe-python/commits{/sha}", "git_commits_url": "https://api.github.com/repos/stripe/stripe-python/git/commits{/sha}", "comments_url": "https://api.github.com/repos/stripe/stripe-python/comments{/number}", "issue_comment_url": "https://api.github.com/repos/stripe/stripe-python/issues/comments{/number}", "contents_url": "https://api.github.com/repos/stripe/stripe-python/contents/{+path}", "compare_url": "https://api.github.com/repos/stripe/stripe-python/compare/{base}...{head}", "merges_url": "https://api.github.com/repos/stripe/stripe-python/merges", "archive_url": "https://api.github.com/repos/stripe/stripe-python/{archive_format}{/ref}", "downloads_url": "https://api.github.com/repos/stripe/stripe-python/downloads", "issues_url": "https://api.github.com/repos/stripe/stripe-python/issues{/number}", "pulls_url": "https://api.github.com/repos/stripe/stripe-python/pulls{/number}", "milestones_url": "https://api.github.com/repos/stripe/stripe-python/milestones{/number}", "notifications_url": "https://api.github.com/repos/stripe/stripe-python/notifications{?since,all,participating}", "labels_url": "https://api.github.com/repos/stripe/stripe-python/labels{/name}", "releases_url": "https://api.github.com/repos/stripe/stripe-python/releases{/id}", "deployments_url": "https://api.github.com/repos/stripe/stripe-python/deployments", "created_at": "2011-06-25T19:53:04Z", "updated_at": "2026-01-17T16:02:23Z", "pushed_at": "2026-01-19T00:25:01Z", "git_url": "git://github.com/stripe/stripe-python.git", "ssh_url": "org-856813@github.com:stripe/stripe-python.git", "clone_url": "https://github.com/stripe/stripe-python.git", "svn_url": "https://github.com/stripe/stripe-python", "homepage": "https://stripe.com", "size": 28946, "stargazers_count": 1941, "watchers_count": 1941, "language": "Python", "has_issues": true, "has_projects": false, "has_downloads": true, "has_wiki": true, "has_pages": false, "has_discussions": false, "forks_count": 484, "mirror_url": null, "archived": false, "disabled": false, "open_issues_count": 20, "license": {"key": "mit", "name": "MIT License", "spdx_id": "MIT", "url": "https://api.github.com/licenses/mit", "node_id": "MDc6TGljZW5zZTEz"}, "allow_forking": true, "is_template": false, "web_commit_signoff_required": false, "topics": ["stripe", "stripe-sdk"], "visibility": "public", "forks": 484, "open_issues": 20, "watchers": 1941, "default_branch": "master"}}, "_links": {"self": {"href": "https://api.github.com/repos/stripe/stripe-python/pulls/1103"}, "html": {"href": "https://github.com/stripe/stripe-python/pull/1103"}, "issue": {"href": "https://api.github.com/repos/stripe/stripe-python/issues/1103"}, "comments": {"href": "https://api.github.com/repos/stripe/stripe-python/issues/1103/comments"}, "review_comments": {"href": "https://api.github.com/repos/stripe/stripe-python/pulls/1103/comments"}, "review_comment": {"href": "https://api.github.com/repos/stripe/stripe-python/pulls/comments{/number}"}, "commits": {"href": "https://api.github.com/repos/stripe/stripe-python/pulls/1103/commits"}, "statuses": {"href": "https://api.github.com/repos/stripe/stripe-python/statuses/1d3498cac13d188af8882b0776a22ffdb4e84f57"}}, "author_association": "CONTRIBUTOR", "auto_merge": null, "active_lock_reason": null, "merged": true, "mergeable": null, "rebaseable": null, "mergeable_state": "unknown", "merged_by": {"login": "richardm-stripe", "id": 52928443, "node_id": "MDQ6VXNlcjUyOTI4NDQz", "avatar_url": "https://avatars.githubusercontent.com/u/52928443?v=4", "gravatar_id": "", "url": "https://api.github.com/users/richardm-stripe", "html_url": "https://github.com/richardm-stripe", "followers_url": "https://api.github.com/users/richardm-stripe/followers", "following_url": "https://api.github.com/users/richardm-stripe/following{/other_user}", "gists_url": "https://api.github.com/users/richardm-stripe/gists{/gist_id}", "starred_url": "https://api.github.com/users/richardm-stripe/starred{/owner}{/repo}", "subscriptions_url": "https://api.github.com/users/richardm-stripe/subscriptions", "organizations_url": "https://api.github.com/users/richardm-stripe/orgs", "repos_url": "https://api.github.com/users/richardm-stripe/repos", "events_url": "https://api.github.com/users/richardm-stripe/events{/privacy}", "received_events_url": "https://api.github.com/users/richardm-stripe/received_events", "type": "User", "user_view_type": "public", "site_admin": false}, "comments": 0, "review_comments": 0, "maintainer_can_modify": false, "commits": 3, "additions": 21326, "deletions": 408, "changed_files": 83}